README.md
setup.py
supercontest/__init__.py
supercontest.egg-info/PKG-INFO
supercontest.egg-info/SOURCES.txt
supercontest.egg-info/dependency_links.txt
supercontest.egg-info/requires.txt
supercontest.egg-info/top_level.txt