Metadata-Version: 2.1
Name: supercontest
Version: 1.0.0
Summary: Client for fetching supercontest data
Home-page: https://github.com/brianmahlstedt/supercontest
Author: Brian Mahlstedt
Author-email: brian.mahlstedt@gmail.com
License: MIT
Keywords: supercontest,football,nfl
Platform: UNKNOWN
